MANIFEST.in
README.rst
setup.py
rbac/__init__.py
rbac/acl.py
rbac/context.py
rbac/proxy.py
simple_rbac_dgb.egg-info/PKG-INFO
simple_rbac_dgb.egg-info/SOURCES.txt
simple_rbac_dgb.egg-info/dependency_links.txt
simple_rbac_dgb.egg-info/top_level.txt
simple_rbac_dgb.egg-info/zip-safe