Metadata-Version: 1.1
Name: simple-rbac-dgb
Version: 0.1.1
Summary: A simple role based access control utility, forked for heavier use of assertions.
Home-page: https://github.com/dbaneman/simple-rbac
Author: Dan Baneman
Author-email: hidden@gmail.com
License: MIT License
Keywords: rbac permission acl access-control
Platform: any
Classifier: Programming Language :: Python
Classifier: Programming Language :: Python :: 2
Classifier: Programming Language :: Python :: 3
Classifier: License :: OSI Approved :: MIT License
Classifier: Operating System :: OS Independent
Classifier: Development Status :: 4 - Beta
Classifier: Intended Audience :: Developers
Classifier: Topic :: Security
Classifier: Topic :: Software Development :: Libraries :: Python Modules
